feincms3_cookiecontrol/__init__.py
feincms3_cookiecontrol/admin.py
feincms3_cookiecontrol/apps.py
feincms3_cookiecontrol/embedding.py
feincms3_cookiecontrol/models.py
feincms3_cookiecontrol/views.py
feincms3_cookiecontrol/locale/de/LC_MESSAGES/django.mo
feincms3_cookiecontrol/locale/de/LC_MESSAGES/django.po
feincms3_cookiecontrol/locale/en/LC_MESSAGES/django.mo
feincms3_cookiecontrol/locale/en/LC_MESSAGES/django.po
feincms3_cookiecontrol/locale/es/LC_MESSAGES/django.mo
feincms3_cookiecontrol/locale/es/LC_MESSAGES/django.po
feincms3_cookiecontrol/locale/fr/LC_MESSAGES/django.mo
feincms3_cookiecontrol/locale/fr/LC_MESSAGES/django.po
feincms3_cookiecontrol/locale/it/LC_MESSAGES/django.mo
feincms3_cookiecontrol/locale/it/LC_MESSAGES/django.po
feincms3_cookiecontrol/locale/rm/LC_MESSAGES/django.mo
feincms3_cookiecontrol/locale/rm/LC_MESSAGES/django.po
feincms3_cookiecontrol/migrations/0001_rework.py
feincms3_cookiecontrol/migrations/__init__.py
feincms3_cookiecontrol/static/f3cc.js
feincms3_cookiecontrol/static/f3cc/gcm.js
feincms3_cookiecontrol/templates/feincms3_cookiecontrol/banner.html
feincms3_cookiecontrol/templates/feincms3_cookiecontrol/embed.html
feincms3_cookiecontrol/templatetags/__init__.py
feincms3_cookiecontrol/templatetags/feincms3_cookiecontrol.py
feincms3_cookiecontrol-1.6.1.dist-info/METADATA
feincms3_cookiecontrol-1.6.1.dist-info/WHEEL
feincms3_cookiecontrol-1.6.1.dist-info/licenses/LICENSE
feincms3_cookiecontrol-1.6.1.dist-info/RECORD
