Metadata-Version: 2.4
Name: feincms3-cookiecontrol
Version: 1.6.1
Summary: Cookie Control Panel for GDPR compliant feincms3 websites
Project-URL: Homepage, https://github.com/feincms/feincms3-cookiecontrol/
Author-email: York Schickl <ys@feinheit.ch>
License: BSD-3-Clause
License-File: LICENSE
Classifier: Environment :: Web Environment
Classifier: Framework :: Django
Classifier: Framework :: Django :: 3.2
Classifier: Framework :: Django :: 4.0
Classifier: Framework :: Django :: 4.1
Classifier: Framework :: Django :: 4.2
Classifier: Framework :: Django :: 5.0
Classifier: Framework :: Django :: 5.1
Classifier: Intended Audience :: Developers
Classifier: License :: OSI Approved :: BSD License
Classifier: Operating System :: OS Independent
Classifier: Programming Language :: Python
Classifier: Programming Language :: Python :: 3 :: Only
Classifier: Programming Language :: Python :: 3.10
Classifier: Programming Language :: Python :: 3.11
Classifier: Programming Language :: Python :: 3.12
Classifier: Programming Language :: Python :: 3.13
Classifier: Topic :: Internet :: WWW/HTTP :: Dynamic Content
Classifier: Topic :: Software Development
Classifier: Topic :: Software Development :: Libraries :: Application Frameworks
Requires-Python: >=3.10
Requires-Dist: django>=3.2
Provides-Extra: embedding
Requires-Dist: feincms3>=5.2.2; extra == 'embedding'
Provides-Extra: tests
Requires-Dist: coverage; extra == 'tests'
Requires-Dist: feincms3>=5.2.2; extra == 'tests'
Requires-Dist: requests; extra == 'tests'
